mlbdatatools/__init__.py
mlbdatatools/datatypes.py
mlbdatatools/mlbfetch.py
mlbdatatools/mlbplot.py
mlbdatatools/utils.py
mlbdatatools-0.1.4.dist-info/LICENSE
mlbdatatools-0.1.4.dist-info/METADATA
mlbdatatools-0.1.4.dist-info/WHEEL
mlbdatatools-0.1.4.dist-info/top_level.txt
mlbdatatools-0.1.4.dist-info/RECORD
